LICENSE.txt
README.md
setup.py
xdot/__init__.py
xdot/__main__.py
xdot.egg-info/PKG-INFO
xdot.egg-info/SOURCES.txt
xdot.egg-info/dependency_links.txt
xdot.egg-info/entry_points.txt
xdot.egg-info/requires.txt
xdot.egg-info/top_level.txt
xdot/dot/__init__.py
xdot/dot/lexer.py
xdot/dot/parser.py
xdot/dot/scanner.py
xdot/ui/__init__.py
xdot/ui/_xdotparser.py
xdot/ui/actions.py
xdot/ui/animation.py
xdot/ui/colors.py
xdot/ui/elements.py
xdot/ui/pen.py
xdot/ui/window.py