Metadata-Version: 2.1
Name: xdot
Version: 1.6
Summary: Interactive viewer for Graphviz dot files
Home-page: https://github.com/jrfonseca/xdot.py
Author: Jose Fonseca
Author-email: jose.r.fonseca@gmail.com
License: LGPL
Platform: UNKNOWN
Classifier: Development Status :: 6 - Mature
Classifier: Environment :: X11 Applications :: GTK
Classifier: Intended Audience :: Information Technology
Classifier: Operating System :: OS Independent
Classifier: License :: OSI Approved :: GNU Lesser General Public License v3 or later (LGPLv3+)
Classifier: Programming Language :: Python :: 3
Classifier: Programming Language :: Python :: 3.4
Classifier: Programming Language :: Python :: 3.5
Classifier: Programming Language :: Python :: 3 :: Only
Classifier: Topic :: Multimedia :: Graphics :: Viewers
License-File: LICENSE.txt
